{
    "key": "group_63f88f8356d33",
    "title": "B: Vote - bar",
    "fields": [
        {
            "key": "field_63f88f943f43e",
            "label": "Info",
            "name": "",
            "aria-label": "",
            "type": "message",
            "instructions": "",
            "required": 0,
            "conditional_logic": 0,
            "wrapper": {
                "width": "",
                "class": "",
                "id": ""
            },
            "message": "Dane pobierane są z zakładki <b>Wygląd >>  Hello Smile settings >> Licznik opinii<\/b>",
            "new_lines": "wpautop",
            "esc_html": 0
        },
        {
            "key": "field_63f88ff03f43f",
            "label": "Wyświetl Badge",
            "name": "wyswietl_badge",
            "aria-label": "",
            "type": "true_false",
            "instructions": "",
            "required": 0,
            "conditional_logic": 0,
            "wrapper": {
                "width": "",
                "class": "",
                "id": ""
            },
            "message": "",
            "default_value": 1,
            "ui_on_text": "",
            "ui_off_text": "",
            "ui": 1
        },
        {
            "key": "field_63f89025e667b",
            "label": "Wyświetlaj Votes",
            "name": "wyswietlaj_vote",
            "aria-label": "",
            "type": "true_false",
            "instructions": "",
            "required": 0,
            "conditional_logic": 0,
            "wrapper": {
                "width": "",
                "class": "",
                "id": ""
            },
            "message": "",
            "default_value": 1,
            "ui_on_text": "",
            "ui_off_text": "",
            "ui": 1
        }
    ],
    "location": [
        [
            {
                "param": "block",
                "operator": "==",
                "value": "acf\/vote-bar"
            }
        ]
    ],
    "menu_order": 0,
    "position": "normal",
    "style": "default",
    "label_placement": "top",
    "instruction_placement": "label",
    "hide_on_screen": "",
    "active": false,
    "description": "",
    "show_in_rest": 0,
    "modified": 1686743114
}